proust/__init__.py
proust/cli.py
proust/core.py
proust/installer.py
proust_framework-1.0.1.dist-info/METADATA
proust_framework-1.0.1.dist-info/WHEEL
proust_framework-1.0.1.dist-info/entry_points.txt
proust_framework-1.0.1.dist-info/licenses/LICENSE
proust_framework-1.0.1.dist-info/RECORD
