Metadata-Version: 2.4
Name: proust-framework
Version: 1.0.1
Summary: AI Memory & Context Archivist - A framework for managing AI context and project memory
Project-URL: Documentation, https://github.com/renkasiyas/proust
Project-URL: Issues, https://github.com/renkasiyas/proust/issues
Project-URL: Source, https://github.com/renkasiyas/proust
Author-email: Ren <ren@example.com>
License-Expression: MIT
License-File: LICENSE
Keywords: ai,context,framework,memory,project-management
Classifier: Development Status :: 4 - Beta
Classifier: Environment :: Console
Classifier: Intended Audience :: Developers
Classifier: License :: OSI Approved :: MIT License
Classifier: Operating System :: OS Independent
Classifier: Programming Language :: Python :: 3
Classifier: Programming Language :: Python :: 3.8
Classifier: Programming Language :: Python :: 3.9
Classifier: Programming Language :: Python :: 3.10
Classifier: Programming Language :: Python :: 3.11
Classifier: Programming Language :: Python :: 3.12
Classifier: Topic :: Software Development :: Documentation
Classifier: Topic :: Software Development :: Libraries :: Python Modules
Classifier: Topic :: Software Development :: Quality Assurance
Requires-Python: >=3.8
Requires-Dist: click>=8.0.0
Requires-Dist: pyyaml>=6.0.0
Requires-Dist: requests>=2.28.0
Provides-Extra: dev
Requires-Dist: black>=22.0.0; extra == 'dev'
Requires-Dist: flake8>=4.0.0; extra == 'dev'
Requires-Dist: mypy>=0.900; extra == 'dev'
Requires-Dist: pytest>=7.0.0; extra == 'dev'
